ChinaParkingLibrary
