Metadata-Version: 1.1
Name: robotframework-chinaParking
Version: 1.0.2
Summary: 新增停车场无感支付模拟接口
Home-page: http://www.chinaparking.com.cn
Author: Greg Wang
Author-email: 30329128@163.com
License: MIT
Platform: UNKNOWN
Classifier: Framework :: Robot Framework
Classifier: Programming Language :: Python
Classifier: Programming Language :: Python :: 2.7
